octopus_deploy_swagger_client/__init__.py
octopus_deploy_swagger_client/api_client.py
octopus_deploy_swagger_client/configuration.py
octopus_deploy_swagger_client/rest.py
octopus_deploy_swagger_client/models/__init__.py
octopus_deploy_swagger_client/models/account_resource.py
octopus_deploy_swagger_client/models/account_usage_resource.py
octopus_deploy_swagger_client/models/action_template_category_resource.py
octopus_deploy_swagger_client/models/action_template_parameter_resource.py
octopus_deploy_swagger_client/models/action_template_resource.py
octopus_deploy_swagger_client/models/action_template_search_resource.py
octopus_deploy_swagger_client/models/action_template_usage_resource.py
octopus_deploy_swagger_client/models/action_update_removed_package_usage.py
octopus_deploy_swagger_client/models/action_update_result_resource.py
octopus_deploy_swagger_client/models/activity_log_element.py
octopus_deploy_swagger_client/models/activity_log_entry.py
octopus_deploy_swagger_client/models/activity_log_tree_node.py
octopus_deploy_swagger_client/models/api_key_resource.py
octopus_deploy_swagger_client/models/artifact_resource.py
octopus_deploy_swagger_client/models/authentication_provider_element.py
octopus_deploy_swagger_client/models/authentication_provider_that_supports_groups.py
octopus_deploy_swagger_client/models/authentication_resource.py
octopus_deploy_swagger_client/models/auto_deploy_release_override_resource.py
octopus_deploy_swagger_client/models/azure_environment_resource.py
octopus_deploy_swagger_client/models/azure_resource_group_resource.py
octopus_deploy_swagger_client/models/azure_storage_account_resource.py
octopus_deploy_swagger_client/models/azure_web_site_resource_azure_web_sites_list_action.py
octopus_deploy_swagger_client/models/azure_web_site_slot_resource.py
octopus_deploy_swagger_client/models/built_in_feed_stats_resource.py
octopus_deploy_swagger_client/models/certificate_configuration_resource.py
octopus_deploy_swagger_client-1.1.0.dist-info/LICENSE
octopus_deploy_swagger_client-1.1.0.dist-info/METADATA
octopus_deploy_swagger_client-1.1.0.dist-info/WHEEL
octopus_deploy_swagger_client-1.1.0.dist-info/top_level.txt
octopus_deploy_swagger_client-1.1.0.dist-info/RECORD
