Metadata-Version: 2.1
Name: octopus-deploy-swagger-client
Version: 1.1.0
Summary: Octopus Server API
Home-page: UNKNOWN
Author: devanjain
Author-email: jain.devan@gmail.com
License: UNKNOWN
Keywords: Swagger,Octopus Server API
Platform: UNKNOWN
Requires-Dist: certifi (>=2017.4.17)
Requires-Dist: python-dateutil (>=2.1)
Requires-Dist: six (>=1.10)
Requires-Dist: urllib3 (>=1.23)
